ITSJwt/__init__.py
ITSJwt/admin.py
ITSJwt/apps.py
ITSJwt/authentication.py
ITSJwt/backends.py
ITSJwt/compat.py
ITSJwt/models.py
ITSJwt/serializers.py
ITSJwt/settings.py
ITSJwt/tests.py
ITSJwt/urls.py
ITSJwt/utils.py
ITSJwt/views.py
ITSJwt/migrations/0001_initial.py
ITSJwt/migrations/__init__.py
django_restframework_jwt_only_use_username-0.0.0.dist-info/METADATA
django_restframework_jwt_only_use_username-0.0.0.dist-info/WHEEL
django_restframework_jwt_only_use_username-0.0.0.dist-info/top_level.txt
django_restframework_jwt_only_use_username-0.0.0.dist-info/RECORD
